{
  "id": "374546a0-1c14-4820-919c-bda993435624",
  "prevId": "45808609-7312-4dd0-b393-833ea2d99a1e",
  "version": "7",
  "dialect": "postgresql",
  "tables": {
    "public.comments": {
      "name": "comments",
      "schema": "",
      "columns": {
        "id": {
          "name": "id",
          "type": "serial",
          "primaryKey": true,
          "notNull": true
        },
        "pen_id": {
          "name": "pen_id",
          "type": "integer",
          "primaryKey": false,
          "notNull": true
        },
        "user_id": {
          "name": "user_id",
          "type": "integer",
          "primaryKey": false,
          "notNull": true
        },
        "content": {
          "name": "content",
          "type": "text",
          "primaryKey": false,
          "notNull": true
        },
        "created_at": {
          "name": "created_at",
          "type": "timestamp",
          "primaryKey": false,
          "notNull": false,
          "default": "now()"
        }
      },
      "indexes": {},
      "foreignKeys": {
        "comments_pen_id_pens_id_fk": {
          "name": "comments_pen_id_pens_id_fk",
          "tableFrom": "comments",
          "tableTo": "pens",
          "columnsFrom": [
            "pen_id"
          ],
          "columnsTo": [
            "id"
          ],
          "onDelete": "no action",
          "onUpdate": "no action"
        },
        "comments_user_id_users_id_fk": {
          "name": "comments_user_id_users_id_fk",
          "tableFrom": "comments",
          "tableTo": "users",
          "columnsFrom": [
            "user_id"
          ],
          "columnsTo": [
            "id"
          ],
          "onDelete": "no action",
          "onUpdate": "no action"
        }
      },
      "compositePrimaryKeys": {},
      "uniqueConstraints": {},
      "policies": {},
      "checkConstraints": {},
      "isRLSEnabled": false
    },
    "public.favorites": {
      "name": "favorites",
      "schema": "",
      "columns": {
        "user_id": {
          "name": "user_id",
          "type": "integer",
          "primaryKey": false,
          "notNull": true
        },
        "pen_id": {
          "name": "pen_id",
          "type": "integer",
          "primaryKey": false,
          "notNull": true
        },
        "created_at": {
          "name": "created_at",
          "type": "timestamp",
          "primaryKey": false,
          "notNull": false,
          "default": "now()"
        }
      },
      "indexes": {},
      "foreignKeys": {
        "favorites_user_id_users_id_fk": {
          "name": "favorites_user_id_users_id_fk",
          "tableFrom": "favorites",
          "tableTo": "users",
          "columnsFrom": [
            "user_id"
          ],
          "columnsTo": [
            "id"
          ],
          "onDelete": "no action",
          "onUpdate": "no action"
        },
        "favorites_pen_id_pens_id_fk": {
          "name": "favorites_pen_id_pens_id_fk",
          "tableFrom": "favorites",
          "tableTo": "pens",
          "columnsFrom": [
            "pen_id"
          ],
          "columnsTo": [
            "id"
          ],
          "onDelete": "no action",
          "onUpdate": "no action"
        }
      },
      "compositePrimaryKeys": {
        "favorites_user_id_pen_id_pk": {
          "name": "favorites_user_id_pen_id_pk",
          "columns": [
            "user_id",
            "pen_id"
          ]
        }
      },
      "uniqueConstraints": {},
      "policies": {},
      "checkConstraints": {},
      "isRLSEnabled": false
    },
    "public.follows": {
      "name": "follows",
      "schema": "",
      "columns": {
        "follower_id": {
          "name": "follower_id",
          "type": "integer",
          "primaryKey": false,
          "notNull": true
        },
        "following_id": {
          "name": "following_id",
          "type": "integer",
          "primaryKey": false,
          "notNull": true
        },
        "created_at": {
          "name": "created_at",
          "type": "timestamp",
          "primaryKey": false,
          "notNull": false,
          "default": "now()"
        }
      },
      "indexes": {},
      "foreignKeys": {
        "follows_follower_id_users_id_fk": {
          "name": "follows_follower_id_users_id_fk",
          "tableFrom": "follows",
          "tableTo": "users",
          "columnsFrom": [
            "follower_id"
          ],
          "columnsTo": [
            "id"
          ],
          "onDelete": "no action",
          "onUpdate": "no action"
        },
        "follows_following_id_users_id_fk": {
          "name": "follows_following_id_users_id_fk",
          "tableFrom": "follows",
          "tableTo": "users",
          "columnsFrom": [
            "following_id"
          ],
          "columnsTo": [
            "id"
          ],
          "onDelete": "no action",
          "onUpdate": "no action"
        }
      },
      "compositePrimaryKeys": {
        "follows_follower_id_following_id_pk": {
          "name": "follows_follower_id_following_id_pk",
          "columns": [
            "follower_id",
            "following_id"
          ]
        }
      },
      "uniqueConstraints": {},
      "policies": {},
      "checkConstraints": {},
      "isRLSEnabled": false
    },
    "public.pen_tags": {
      "name": "pen_tags",
      "schema": "",
      "columns": {
        "pen_id": {
          "name": "pen_id",
          "type": "integer",
          "primaryKey": false,
          "notNull": true
        },
        "tag_id": {
          "name": "tag_id",
          "type": "integer",
          "primaryKey": false,
          "notNull": true
        }
      },
      "indexes": {},
      "foreignKeys": {
        "pen_tags_pen_id_pens_id_fk": {
          "name": "pen_tags_pen_id_pens_id_fk",
          "tableFrom": "pen_tags",
          "tableTo": "pens",
          "columnsFrom": [
            "pen_id"
          ],
          "columnsTo": [
            "id"
          ],
          "onDelete": "cascade",
          "onUpdate": "no action"
        },
        "pen_tags_tag_id_tags_id_fk": {
          "name": "pen_tags_tag_id_tags_id_fk",
          "tableFrom": "pen_tags",
          "tableTo": "tags",
          "columnsFrom": [
            "tag_id"
          ],
          "columnsTo": [
            "id"
          ],
          "onDelete": "no action",
          "onUpdate": "no action"
        }
      },
      "compositePrimaryKeys": {
        "pen_tags_pen_id_tag_id_pk": {
          "name": "pen_tags_pen_id_tag_id_pk",
          "columns": [
            "pen_id",
            "tag_id"
          ]
        }
      },
      "uniqueConstraints": {},
      "policies": {},
      "checkConstraints": {},
      "isRLSEnabled": false
    },
    "public.pens": {
      "name": "pens",
      "schema": "",
      "columns": {
        "id": {
          "name": "id",
          "type": "integer",
          "primaryKey": true,
          "notNull": true,
          "identity": {
            "type": "always",
            "name": "pens_id_seq",
            "schema": "public",
            "increment": "1",
            "startWith": "1",
            "minValue": "1",
            "maxValue": "2147483647",
            "cache": "1",
            "cycle": false
          }
        },
        "user_id": {
          "name": "user_id",
          "type": "integer",
          "primaryKey": false,
          "notNull": false
        },
        "html_code": {
          "name": "html_code",
          "type": "text",
          "primaryKey": false,
          "notNull": false
        },
        "css_code": {
          "name": "css_code",
          "type": "text",
          "primaryKey": false,
          "notNull": false
        },
        "js_code": {
          "name": "js_code",
          "type": "text",
          "primaryKey": false,
          "notNull": false
        },
        "title": {
          "name": "title",
          "type": "varchar(100)",
          "primaryKey": false,
          "notNull": true
        },
        "description": {
          "name": "description",
          "type": "text",
          "primaryKey": false,
          "notNull": false
        },
        "is_private": {
          "name": "is_private",
          "type": "boolean",
          "primaryKey": false,
          "notNull": false,
          "default": false
        },
        "created_at": {
          "name": "created_at",
          "type": "timestamp",
          "primaryKey": false,
          "notNull": false,
          "default": "now()"
        }
      },
      "indexes": {},
      "foreignKeys": {
        "pens_user_id_users_id_fk": {
          "name": "pens_user_id_users_id_fk",
          "tableFrom": "pens",
          "tableTo": "users",
          "columnsFrom": [
            "user_id"
          ],
          "columnsTo": [
            "id"
          ],
          "onDelete": "no action",
          "onUpdate": "no action"
        }
      },
      "compositePrimaryKeys": {},
      "uniqueConstraints": {},
      "policies": {},
      "checkConstraints": {},
      "isRLSEnabled": false
    },
    "public.tags": {
      "name": "tags",
      "schema": "",
      "columns": {
        "id": {
          "name": "id",
          "type": "serial",
          "primaryKey": true,
          "notNull": true
        },
        "name": {
          "name": "name",
          "type": "varchar(50)",
          "primaryKey": false,
          "notNull": true
        }
      },
      "indexes": {},
      "foreignKeys": {},
      "compositePrimaryKeys": {},
      "uniqueConstraints": {
        "tags_name_unique": {
          "name": "tags_name_unique",
          "nullsNotDistinct": false,
          "columns": [
            "name"
          ]
        }
      },
      "policies": {},
      "checkConstraints": {},
      "isRLSEnabled": false
    },
    "public.users": {
      "name": "users",
      "schema": "",
      "columns": {
        "id": {
          "name": "id",
          "type": "integer",
          "primaryKey": true,
          "notNull": true,
          "identity": {
            "type": "always",
            "name": "users_id_seq",
            "schema": "public",
            "increment": "1",
            "startWith": "1",
            "minValue": "1",
            "maxValue": "2147483647",
            "cache": "1",
            "cycle": false
          }
        },
        "email": {
          "name": "email",
          "type": "varchar(255)",
          "primaryKey": false,
          "notNull": true
        },
        "username": {
          "name": "username",
          "type": "varchar(50)",
          "primaryKey": false,
          "notNull": true
        },
        "password_hash": {
          "name": "password_hash",
          "type": "text",
          "primaryKey": false,
          "notNull": true
        },
        "is_pro": {
          "name": "is_pro",
          "type": "boolean",
          "primaryKey": false,
          "notNull": false,
          "default": false
        },
        "profile_image": {
          "name": "profile_image",
          "type": "text",
          "primaryKey": false,
          "notNull": false
        },
        "display_name": {
          "name": "display_name",
          "type": "varchar(100)",
          "primaryKey": false,
          "notNull": false
        },
        "bio": {
          "name": "bio",
          "type": "text",
          "primaryKey": false,
          "notNull": false
        },
        "profile_link1": {
          "name": "profile_link1",
          "type": "text",
          "primaryKey": false,
          "notNull": false
        },
        "profile_link2": {
          "name": "profile_link2",
          "type": "text",
          "primaryKey": false,
          "notNull": false
        },
        "profile_link3": {
          "name": "profile_link3",
          "type": "text",
          "primaryKey": false,
          "notNull": false
        },
        "created_at": {
          "name": "created_at",
          "type": "timestamp",
          "primaryKey": false,
          "notNull": false,
          "default": "now()"
        }
      },
      "indexes": {},
      "foreignKeys": {},
      "compositePrimaryKeys": {},
      "uniqueConstraints": {
        "users_email_unique": {
          "name": "users_email_unique",
          "nullsNotDistinct": false,
          "columns": [
            "email"
          ]
        }
      },
      "policies": {},
      "checkConstraints": {},
      "isRLSEnabled": false
    }
  },
  "enums": {},
  "schemas": {},
  "sequences": {},
  "roles": {},
  "policies": {},
  "views": {},
  "_meta": {
    "columns": {},
    "schemas": {},
    "tables": {}
  }
}